tm_deep_utilities/__init__.py
tm_deep_utilities/pipeline_logging/__init__.py
tm_deep_utilities/pipeline_logging/logging_functions.py
tm_deep_utilities/storage/__init__.py
tm_deep_utilities/storage/storage_functions.py
tm_deep_utilities/transformation/__init__.py
tm_deep_utilities/transformation/transformation_functions.py
tm_deep_utilities-0.2.0.dist-info/METADATA
tm_deep_utilities-0.2.0.dist-info/WHEEL
tm_deep_utilities-0.2.0.dist-info/top_level.txt
tm_deep_utilities-0.2.0.dist-info/RECORD
